SSHLibrary/__init__.py
SSHLibrary/abstractclient.py
SSHLibrary/byte_handler.py
SSHLibrary/client.py
SSHLibrary/config.py
SSHLibrary/javaclient.py
SSHLibrary/library.py
SSHLibrary/pythonclient.py
SSHLibrary/version.py
robotframework_sshlibrary_py3-2.1.4.dev0.dist-info/DESCRIPTION.rst
robotframework_sshlibrary_py3-2.1.4.dev0.dist-info/METADATA
robotframework_sshlibrary_py3-2.1.4.dev0.dist-info/RECORD
robotframework_sshlibrary_py3-2.1.4.dev0.dist-info/WHEEL
robotframework_sshlibrary_py3-2.1.4.dev0.dist-info/metadata.json
robotframework_sshlibrary_py3-2.1.4.dev0.dist-info/top_level.txt
