Metadata-Version: 2.0
Name: robotframework-sshlibrary-py3
Version: 2.1.4.dev0
Summary: Robot Framework test library for SSH and SFTP
Home-page: https://github.com/Brian-Williams/SSHLibrary
Author: Robot Framework Developers
Author-email: robotframework@gmail.com
License: Apache License 2.0
Keywords: robotframework testing testautomation ssh sftp
Platform: any
Classifier: Development Status :: 5 - Production/Stable
Classifier: License :: OSI Approved :: Apache Software License
Classifier: Operating System :: OS Independent
Classifier: Programming Language :: Python
Classifier: Topic :: Software Development :: Testing
Requires-Dist: paramiko (>=1.8.0)
Requires-Dist: robotframework
